{
  "label": "Italian",
  "forms": {
    "JACKET": { "form": "giacca", "gender": "f", "plural": "giacche" },
    "DRESS": { "form": "vestito", "gender": "m", "plural": "vestiti" },
    "SNEAKERS": { "form": "sneakers", "gender": "f", "plural": "sneakers" },
    "FABRIC": { "form": "tessuto", "gender": "m", "plural": "tessuti" },
    "LEATHER": { "form": "pelle", "gender": "f", "plural": "pelli" },
    "SILK": { "form": "seta", "gender": "f", "plural": "sete" },
    "PATTERN": { "form": "motivo", "gender": "m", "plural": "motivi" },
    "STITCH": { "form": "punto", "gender": "m", "plural": "punti" },
    "TAILOR": { "form": "sarto", "gender": "m", "plural": "sarti" },
    "RUNWAY": { "form": "passerella", "gender": "f", "plural": "passerelle" },
    "MODEL": { "form": "modello", "gender": "m", "plural": "modelli" },
    "COLLECTION": { "form": "collezione", "gender": "f", "plural": "collezioni" },
    "BOUTIQUE": { "form": "boutique", "gender": "f", "plural": "boutique" },
    "WARDROBE": { "form": "guardaroba", "gender": "m", "plural": "guardaroba" },
    "TREND": { "form": "tendenza", "gender": "f", "plural": "tendenze" },
    "NECKLACE": { "form": "collana", "gender": "f", "plural": "collane" },
    "BRACELET": { "form": "braccialetto", "gender": "m", "plural": "braccialetti" },
    "SUNGLASSES": { "form": "occhiali da sole", "gender": "m", "plural": "occhiali da sole" },
    "MAKEUP": { "form": "trucco", "gender": "m", "plural": "trucchi" },
    "LIPSTICK": { "form": "rossetto", "gender": "m", "plural": "rossetti" },
    "HAIRSTYLE": { "form": "acconciatura", "gender": "f", "plural": "acconciature" },
    "OUTFIT": { "form": "outfit", "gender": "m", "plural": "outfit" },
    "LOOKBOOK": { "form": "lookbook", "gender": "m", "plural": "lookbook" },
    "AESTHETIC": { "form": "estetica", "gender": "f", "plural": "estetiche" },
    "DESIGNER": { "form": "stilista", "gender": "m", "plural": "stilisti" },
    "BRAND": { "form": "marca", "gender": "f", "plural": "marche" },
    "CAMPAIGN": { "form": "campagna", "gender": "f", "plural": "campagne" },
    "INFLUENCER": { "form": "influencer", "gender": "m", "plural": "influencer" },
    "EDITORIAL": { "form": "editoriale", "gender": "m", "plural": "editoriali" },
    "COUTURE": { "form": "haute couture", "gender": "f", "plural": "haute couture" },
    "EMBROIDER": { "base": "ricamare", "1_singular": "ricamo", "2_singular": "ricami", "3_singular": "ricama", "1_plural": "ricamiamo", "2_plural": "ricamate", "3_plural": "ricamano" },
    "DRAPE": { "base": "drappeggiare", "1_singular": "drappeggio", "2_singular": "drappeggi", "3_singular": "drappeggia", "1_plural": "drappeggiamo", "2_plural": "drappeggiate", "3_plural": "drappeggiano" },
    "DESIGN": { "base": "disegnare", "1_singular": "disegno", "2_singular": "disegni", "3_singular": "disegna", "1_plural": "disegniamo", "2_plural": "disegnate", "3_plural": "disegnano" },
    "STRUT": { "base": "sfilare", "1_singular": "sfilo", "2_singular": "sfili", "3_singular": "sfila", "1_plural": "sfiliamo", "2_plural": "sfilate", "3_plural": "sfilano" },
    "BROWSE": { "base": "curiosare", "1_singular": "curioso", "2_singular": "curiosi", "3_singular": "curiosa", "1_plural": "curiosiamo", "2_plural": "curiosate", "3_plural": "curiosano" },
    "ADORN": { "base": "adornare", "1_singular": "adorno", "2_singular": "adorni", "3_singular": "adorna", "1_plural": "adorniamo", "2_plural": "adornate", "3_plural": "adornano" },
    "CONTOUR": { "base": "contornare", "1_singular": "contorno", "2_singular": "contorni", "3_singular": "contorna", "1_plural": "contorniamo", "2_plural": "contornate", "3_plural": "contornano" },
    "COORDINATE": { "base": "coordinare", "1_singular": "coordino", "2_singular": "coordini", "3_singular": "coordina", "1_plural": "coordiniamo", "2_plural": "coordinate", "3_plural": "coordinano" },
    "UNVEIL": { "base": "svelare", "1_singular": "svelo", "2_singular": "sveli", "3_singular": "svela", "1_plural": "sveliamo", "2_plural": "svelate", "3_plural": "svelano" },
    "SHOWCASE": { "base": "presentare", "1_singular": "presento", "2_singular": "presenti", "3_singular": "presenta", "1_plural": "presentiamo", "2_plural": "presentate", "3_plural": "presentano" },
    "ELEGANT": [ "elegante" ],
    "TEXTURED": [ "testurizzato" ],
    "VINTAGE": [ "vintage" ],
    "GLAMOROUS": [ "glamour" ],
    "AFFORDABLE": [ "accessibile" ],
    "DAZZLING": [ "abbagliante" ],
    "FLAWLESS": [ "impeccabile" ],
    "CHIC": [ "chic" ],
    "EXCLUSIVE": [ "esclusivo" ],
    "ICONIC": [ "iconico" ]
  }
}
