{
  "label": "Greek",
  "forms": {
    "POKEMON": { "form": "Πόκεμον", "gender": "n", "plural": "Πόκεμον" },
    "TRAINER": { "form": "εκπαιδευτής", "gender": "m", "plural": "εκπαιδευτές" },
    "GYM": { "form": "γυμναστήριο", "gender": "n", "plural": "γυμναστήρια" },
    "LEAGUE": { "form": "λίγκα", "gender": "f", "plural": "λίγκες" },
    "GYM_LEADER": { "form": "αρχηγός γυμναστηρίου", "gender": "m", "plural": "αρχηγοί γυμναστηρίου" },
    "ELITE_FOUR": { "form": "ελίτ τέσσερα", "gender": "n", "plural": "ελίτ τέσσερα" },
    "POKEMON_CENTER": { "form": "κέντρο Πόκεμον", "gender": "n", "plural": "κέντρα Πόκεμον" },
    "FOREST": { "form": "δάσος", "gender": "n", "plural": "δάση" },
    "CAVE": { "form": "σπηλιά", "gender": "f", "plural": "σπηλιές" },
    "TOWN": { "form": "πόλη", "gender": "f", "plural": "πόλεις" },
    "BATTLE": { "form": "μάχη", "gender": "f", "plural": "μάχες" },
    "MOVE": { "form": "κίνηση", "gender": "f", "plural": "κινήσεις" },
    "DAMAGE": { "form": "ζημιά", "gender": "f", "plural": "ζημιές" },
    "DEFENSE": { "form": "άμυνα", "gender": "f", "plural": "άμυνες" },
    "SPEED": { "form": "ταχύτητα", "gender": "f", "plural": "ταχύτητες" },
    "STAT": { "form": "στατιστικό", "gender": "n", "plural": "στατιστικά" },
    "ABILITY": { "form": "ικανότητα", "gender": "f", "plural": "ικανότητες" },
    "TYPE": { "form": "τύπος", "gender": "m", "plural": "τύποι" },
    "POTION": { "form": "φίλτρο", "gender": "n", "plural": "φίλτρα" },
    "REVIVE": { "form": "αναζωογόνηση", "gender": "f", "plural": "αναζωογονήσεις" },
    "TECHNICAL_MACHINE": { "form": "τεχνική μηχανή", "gender": "f", "plural": "τεχνικές μηχανές" },
    "BADGE": { "form": "σήμα", "gender": "n", "plural": "σήματα" },
    "ITEM": { "form": "αντικείμενο", "gender": "n", "plural": "αντικείμενα" },
    "LEVEL": { "form": "επίπεδο", "gender": "n", "plural": "επίπεδα" },
    "EXPERIENCE": { "form": "εμπειρία", "gender": "f", "plural": "εμπειρίες" },
    "HEALTH": { "form": "υγεία", "gender": "f", "plural": "υγείες" },
    "BURN": { "base": "καίω", "1_singular": "καίω", "2_singular": "καις", "3_singular": "καίει", "1_plural": "καίμε", "2_plural": "καίτε", "3_plural": "καίνε" },
    "POISON": { "base": "δηλητηριάζω", "1_singular": "δηλητηριάζω", "2_singular": "δηλητηριάζεις", "3_singular": "δηλητηριάζει", "1_plural": "δηλητηριάζουμε", "2_plural": "δηλητηριάζετε", "3_plural": "δηλητηριάζουν" },
    "SLEEP_STATUS": { "form": "ύπνος", "gender": "m", "plural": "ύπνοι" },
    "PARALYZE": { "base": "παραλύω", "1_singular": "παραλύω", "2_singular": "παραλύεις", "3_singular": "παραλύει", "1_plural": "παραλύουμε", "2_plural": "παραλύετε", "3_plural": "παραλύουν" },
    "SEEN": { "form": "ειδωμένα", "gender": "n", "plural": "ειδωμένα" },
    "CAPTURED": { "form": "πιασμένα", "gender": "n", "plural": "πιασμένα" },
    "ATTACK": { "base": "επιτίθεμαι", "1_singular": "επιτίθεμαι", "2_singular": "επιτίθεσαι", "3_singular": "επιτίθεται", "1_plural": "επιτιθέμαστε", "2_plural": "επιτίθεστε", "3_plural": "επιτίθενται" },
    "RUN": { "base": "τρέχω", "1_singular": "τρέχω", "2_singular": "τρέχεις", "3_singular": "τρέχει", "1_plural": "τρέχουμε", "2_plural": "τρέχετε", "3_plural": "τρέχουν" },
    "CATCH": { "base": "πιάνω", "1_singular": "πιάνω", "2_singular": "πιάνεις", "3_singular": "πιάνει", "1_plural": "πιάνουμε", "2_plural": "πιάνετε", "3_plural": "πιάνουν" },
    "DEFEAT": { "base": "νικώ", "1_singular": "νικώ", "2_singular": "νικάς", "3_singular": "νικά", "1_plural": "νικάμε", "2_plural": "νικάτε", "3_plural": "νικούν" },
    "SWITCH": { "base": "αλλάζω", "1_singular": "αλλάζω", "2_singular": "αλλάζεις", "3_singular": "αλλάζει", "1_plural": "αλλάζουμε", "2_plural": "αλλάζετε", "3_plural": "αλλάζουν" },
    "USE": { "base": "χρησιμοποιώ", "1_singular": "χρησιμοποιώ", "2_singular": "χρησιμοποιείς", "3_singular": "χρησιμοποιεί", "1_plural": "χρησιμοποιούμε", "2_plural": "χρησιμοποιείτε", "3_plural": "χρησιμοποιούν" },
    "FLY": { "base": "πετώ", "1_singular": "πετώ", "2_singular": "πετάς", "3_singular": "πετά", "1_plural": "πετάμε", "2_plural": "πετάτε", "3_plural": "πετούν" },
    "PLAY": { "base": "παίζω", "1_singular": "παίζω", "2_singular": "παίζεις", "3_singular": "παίζει", "1_plural": "παίζουμε", "2_plural": "παίζετε", "3_plural": "παίζουν" },
    "HEAL": { "base": "θεραπεύω", "1_singular": "θεραπεύω", "2_singular": "θεραπεύεις", "3_singular": "θεραπεύει", "1_plural": "θεραπεύουμε", "2_plural": "θεραπεύετε", "3_plural": "θεραπεύουν" },
    "RESTORE": { "base": "επαναφέρω", "1_singular": "επαναφέρω", "2_singular": "επαναφέρεις", "3_singular": "επαναφέρει", "1_plural": "επαναφέρουμε", "2_plural": "επαναφέρετε", "3_plural": "επαναφέρουν" },
    "GAIN_EXPERIENCE": { "base": "κερδίζω εμπειρία", "1_singular": "κερδίζω εμπειρία", "2_singular": "κερδίζεις εμπειρία", "3_singular": "κερδίζει εμπειρία", "1_plural": "κερδίζουμε εμπειρία", "2_plural": "κερδίζετε εμπειρία", "3_plural": "κερδίζουν εμπειρία" },
    "EVOLVE": { "base": "εξελίσσομαι", "1_singular": "εξελίσσομαι", "2_singular": "εξελίσσεσαι", "3_singular": "εξελίσσεται", "1_plural": "εξελισσόμαστε", "2_plural": "εξελίσσεστε", "3_plural": "εξελίσσονται" },
    "WILD": [ "άγριος" ],
    "STRONG": [ "δυνατός" ],
    "EFFECTIVE": [ "αποτελεσματικός" ],
    "SUPER_EFFECTIVE": [ "πολύ αποτελεσματικός" ],
    "VERY_EFFECTIVE": [ "εξαιρετικά αποτελεσματικός" ],
    "LEGENDARY": [ "θρυλικός" ],
    "SHINY": [ "αστραφτερός" ]
  }
}
